flask_gunicorn_cmd/__init__.py
flask_gunicorn_cmd/main.py
flask_gunicorn_cmd-0.0.6.dist-info/LICENSE
flask_gunicorn_cmd-0.0.6.dist-info/METADATA
flask_gunicorn_cmd-0.0.6.dist-info/WHEEL
flask_gunicorn_cmd-0.0.6.dist-info/entry_points.txt
flask_gunicorn_cmd-0.0.6.dist-info/top_level.txt
flask_gunicorn_cmd-0.0.6.dist-info/RECORD
