Metadata-Version: 2.1
Name: flask-gunicorn-cmd
Version: 0.0.6
Summary: Command line wrapper to run a named Flask script inside a Gunicorn server
Home-page: https://github.com/ideonate/flask-gunicorn-cmd
Author: Dan Lester
Author-email: dan@ideonate.com
License: UNKNOWN
Platform: UNKNOWN
Classifier: Programming Language :: Python :: 3
Classifier: License :: OSI Approved :: MIT License
Classifier: Operating System :: OS Independent
Requires-Python: >=3.6
Requires-Dist: gunicorn
Requires-Dist: Click (>=7.0)
